setup.cfg
setup.py
src/pd_observer/__init__.py
src/pd_observer/__main__.py
src/pd_observer/cli.py
src/pd_observer.egg-info/PKG-INFO
src/pd_observer.egg-info/SOURCES.txt
src/pd_observer.egg-info/dependency_links.txt
src/pd_observer.egg-info/entry_points.txt
src/pd_observer.egg-info/not-zip-safe
src/pd_observer.egg-info/requires.txt
src/pd_observer.egg-info/top_level.txt